wyltools
