Metadata-Version: 1.0
Name: wyltools
Version: 1.0.1
Summary: 常用方法工具箱
Home-page: https://github.com/evo-cus/wyl-tools
Author: yanlei.wang
Author-email: wangyalei310@163.com
License: UNKNOWN
Platform: UNKNOWN
